README.md
setup.py
flask_mongoengine_orm/__init__.py
flask_mongoengine_orm/orm.py
flask_mongoengine_orm.egg-info/PKG-INFO
flask_mongoengine_orm.egg-info/SOURCES.txt
flask_mongoengine_orm.egg-info/dependency_links.txt
flask_mongoengine_orm.egg-info/requires.txt
flask_mongoengine_orm.egg-info/top_level.txt